ase_util/__init__.py
ase_util/aseLearn.py
ase_util/aseMDLearn.py
ase_util/aseTutorial.py
ase_util-0.1.2.dist-info/METADATA
ase_util-0.1.2.dist-info/WHEEL
ase_util-0.1.2.dist-info/RECORD
